<?xml version="1.0" encoding="utf-8" ?>
<Dictionary>
	<!--
	<Acronyms>
		<CasingExceptions>
			<Acronym>CMS</Acronym>
			<Acronym>Io</Acronym>
			<Acronym>Param</Acronym>
      <Acronym>Ui</Acronym>
		</CasingExceptions>
	</Acronyms>
	<Words>
		<DiscreteExceptions>
			<Term>epi</Term>
		</DiscreteExceptions>
		<Recognized>
			<Word>api</Word>
			<Word>cms</Word>
			<Word>concatenator</Word>
			<Word>dds</Word>
			<Word>editmode</Word>
			<Word>epi</Word>
			<Word>expr</Word>
			<Word>favourites</Word>
			<Word>headlinable</Word>
			<Word>initializable</Word>
			<Word>lan</Word>
			<Word>län</Word>
			<Word>mvc</Word>
			<Word>oll</Word>
			<Word>param</Word>
			<Word>personalizable</Word>
			<Word>possessivate</Word>
			<Word>rss</Word>
			<Word>subscribable</Word>
			<Word>trackable</Word>
			<Word>treshold</Word>
			<Word>unescaped</Word>
			<Word>unescapes</Word>
			<Word>unpersonalizable</Word>
			<Word>versionable</Word>
			<Word>öll</Word>
			<Word>örebro</Word>
			<Word>::</Word>
			<Word>xFormpostedData</Word>
			<Word>Formposted</Word>
			<Word>x</Word>
			<Word>telefonist</Word>
			<Word>Ean</Word>
			<Word>Mixins</Word>
			<Word>Infos</Word>
			<Word>Informations</Word>
			<Word>Expirable</Word>
			<Word>Hsa</Word>
			<Word>Platina</Word>
			<Word>Augmentor</Word>
			<Word>Multi</Word>
			<Word>Taggable</Word>
			<Word>Util</Word>
			<Word>Mce</Word>
			<Word>Shortcuttable</Word>
			<Word>gammeldokument</Word>
			<Word>dokument</Word>
			<Word>ev</Word>
		</Recognized>
	</Words>
	-->
	<Words>
		<DiscreteExceptions>
			<Term>PlaceHolder</Term>
		</DiscreteExceptions>
		<Recognized>
			<Word>mvc</Word>
			<Word>util</Word>
		</Recognized>
	</Words>
</Dictionary>